bin/__init__.py
bin/memacs_arbtt.py
bin/memacs_battery.py
bin/memacs_chrome.py
bin/memacs_csv.py
bin/memacs_example.py
bin/memacs_filenametimestamps.py
bin/memacs_firefox.py
bin/memacs_git.py
bin/memacs_gpx.py
bin/memacs_ical.py
bin/memacs_imap.py
bin/memacs_kodi.py
bin/memacs_lastfm.py
bin/memacs_mumail.py
bin/memacs_phonecalls.py
bin/memacs_phonecalls_superbackup.py
bin/memacs_photos.py
bin/memacs_rss.py
bin/memacs_simplephonelogs.py
bin/memacs_sms.py
bin/memacs_sms_superbackup.py
bin/memacs_svn.py
bin/memacs_twitter.py
bin/memacs_whatsapp.py
memacs/__init__.py
memacs/arbtt.py
memacs/battery.py
memacs/chrome.py
memacs/csv.py
memacs/example.py
memacs/filenametimestamps.py
memacs/firefox.py
memacs/git.py
memacs/gpx.py
memacs/ical.py
memacs/imap.py
memacs/kodi.py
memacs/lastfm.py
memacs/mu.py
memacs/phonecalls.py
memacs/phonecalls_superbackup.py
memacs/photos.py
memacs/rss.py
memacs/simplephonelogs.py
memacs/sms.py
memacs/sms_superbackup.py
memacs/svn.py
memacs/twitter.py
memacs/whatsapp.py
memacs/lib/__init__.py
memacs/lib/argparser.py
memacs/lib/contactparser.py
memacs/lib/loggingsettings.py
memacs/lib/mailparser.py
memacs/lib/memacs.py
memacs/lib/orgformat.py
memacs/lib/orgproperty.py
memacs/lib/orgwriter.py
memacs/lib/reader.py
memacs/lib/tests/__init__.py
memacs/lib/tests/argparser_test.py
memacs/lib/tests/mailparser_test.py
memacs/lib/tests/orgproperty_test.py
memacs/lib/tests/orgwriter_test.py
memacs/lib/tests/reader_test.py
memacs/tests/__init__.py
memacs/tests/arbtt_test.py
memacs/tests/battery_test.py
memacs/tests/csv_test.py
memacs/tests/example_test.py
memacs/tests/filenametimestamps_test.py
memacs/tests/git_test.py
memacs/tests/gpx_test.py
memacs/tests/ical_test.py
memacs/tests/phonecalls_superbackup_test.py
memacs/tests/phonecalls_test.py
memacs/tests/photos_test.py
memacs/tests/rss_test.py
memacs/tests/simplephonelogs_test.py
memacs/tests/sms_test.py
memacs/tests/svn_test.py
memacs/tests/whatsapp_test.py
memacs-2022.8.6.dist-info/METADATA
memacs-2022.8.6.dist-info/WHEEL
memacs-2022.8.6.dist-info/entry_points.txt
memacs-2022.8.6.dist-info/top_level.txt
memacs-2022.8.6.dist-info/RECORD
