Metadata-Version: 2.1
Name: memacs
Version: 2022.8.6
Summary: Visualize your (digital) life in Emacs Org mode by converting data to Org mode format
Home-page: https://github.com/novoid/memacs
Author: Karl Voit
Author-email: tools@Karl-Voit.at
License: UNKNOWN
Download-URL: https://github.com/novoid/memacs/zipball/master
Keywords: quantified self,emacs,org-mode,org mode
Platform: UNKNOWN
Classifier: Programming Language :: Python :: 3 :: Only
Classifier: Development Status :: 5 - Production/Stable
Classifier: Environment :: Console
Classifier: Intended Audience :: End Users/Desktop
Classifier: License :: OSI Approved :: GNU General Public License (GPL)
Classifier: Operating System :: OS Independent
Requires-Dist: emoji
Requires-Dist: orgformat
Provides-Extra: all
Requires-Dist: batinfo ; extra == 'all'
Requires-Dist: feedparser ; extra == 'all'
Requires-Dist: geocoder ; extra == 'all'
Requires-Dist: gpxpy ; extra == 'all'
Requires-Dist: icalendar ; extra == 'all'
Requires-Dist: pylast ; extra == 'all'
Requires-Dist: python-dateutil ; extra == 'all'
Requires-Dist: twython ; extra == 'all'
Provides-Extra: battery
Requires-Dist: batinfo ; extra == 'battery'
Provides-Extra: gps
Requires-Dist: geocoder ; extra == 'gps'
Requires-Dist: gpxpy ; extra == 'gps'
Provides-Extra: ical
Requires-Dist: icalendar ; extra == 'ical'
Provides-Extra: lastfm
Requires-Dist: pylast ; extra == 'lastfm'
Provides-Extra: rss
Requires-Dist: feedparser ; extra == 'rss'
Provides-Extra: twitter
Requires-Dist: python-dateutil ; extra == 'twitter'
Requires-Dist: twython ; extra == 'twitter'
